{"ongoing_trials": {}, "hyperparameters": {"space": [{"class_name": "Int", "config": {"name": "n_hidden", "default": 2, "conditions": [], "min_value": 0, "max_value": 8, "step": 1, "sampling": "linear"}}, {"class_name": "Int", "config": {"name": "n_neurons", "default": null, "conditions": [], "min_value": 32, "max_value": 64, "step": 1, "sampling": "linear"}}, {"class_name": "Float", "config": {"name": "learning_rate", "default": 0.001, "conditions": [], "min_value": 0.001, "max_value": 0.002, "step": null, "sampling": "log"}}, {"class_name": "Choice", "config": {"name": "optimizer", "default": "sgd", "conditions": [], "values": ["sgd", "adam"], "ordered": false}}], "values": {"n_hidden": 2, "n_neurons": 32, "learning_rate": 0.001, "optimizer": "sgd"}}, "start_order": ["00", "01", "02", "03", "04", "05", "06", "07", "08", "09"], "end_order": ["00", "01", "02", "03", "04", "05", "06", "07", "08", "09"], "run_times": {"00": 1, "01": 1, "02": 1, "03": 1, "04": 1, "05": 1, "06": 1, "07": 1, "08": 1, "09": 1}, "retry_queue": [], "seed": 42, "seed_state": 82, "tried_so_far": ["a9de758c26b91544b554ebc8b358730b", "41e0cb3aab014aee16424ba7f38ac71b", "0bed057c88b3f906c410765c0e9b21eb", "de53940c8b681f36f06e9c9c231addc4", "153aa36d07fbd7b4c934095c95dedb99", "0b315b3f0ae91b99b0ec44466823c558", "07cbb215a8f38991fbbc07f5510d7e59", "db4ddd8552a54178922e1f77a8b840f6", "4a439c0ca22ea73705a2343a7e852e21", "a91b45201aa571b2f40d1acc9fd0118a"], "id_to_hash": {"00": "0b315b3f0ae91b99b0ec44466823c558", "01": "41e0cb3aab014aee16424ba7f38ac71b", "02": "a91b45201aa571b2f40d1acc9fd0118a", "03": "07cbb215a8f38991fbbc07f5510d7e59", "04": "4a439c0ca22ea73705a2343a7e852e21", "05": "db4ddd8552a54178922e1f77a8b840f6", "06": "de53940c8b681f36f06e9c9c231addc4", "07": "153aa36d07fbd7b4c934095c95dedb99", "08": "a9de758c26b91544b554ebc8b358730b", "09": "0bed057c88b3f906c410765c0e9b21eb"}, "display": {"search_start": "2023-12-07T02:30:43.192433", "trial_start": {"00": "2023-12-07T02:30:43.192433", "01": "2023-12-07T02:30:59.779242", "02": "2023-12-07T02:31:22.413108", "03": "2023-12-07T02:31:37.106545", "04": "2023-12-07T02:32:01.878981", "05": "2023-12-07T02:32:18.821183", "06": "2023-12-07T02:32:43.805562", "07": "2023-12-07T02:32:50.543848", "08": "2023-12-07T02:33:15.550752", "09": "2023-12-07T02:33:39.580460"}, "trial_number": {"00": 1, "01": 2, "02": 3, "03": 4, "04": 5, "05": 6, "06": 7, "07": 8, "08": 9, "09": 10}}}